multicarriage/__init__.py
multicarriage/demo.py
multicarriage/main.py
multicarriage-1.1.dist-info/LICENSE
multicarriage-1.1.dist-info/METADATA
multicarriage-1.1.dist-info/WHEEL
multicarriage-1.1.dist-info/top_level.txt
multicarriage-1.1.dist-info/RECORD
