Metadata-Version: 2.1
Name: multicarriage
Version: 1.1
Summary: Allows the ability to rewrite multiple lines via carriage returns.
Home-page: https://github.com/xyzpw/multicarriage
Author: xyzpw
Maintainer: xyzpw
License: MIT
Classifier: Operating System :: POSIX :: Linux
Classifier: Topic :: Utilities
Classifier: Intended Audience :: Developers
Classifier: Programming Language :: Python :: 3.7
Classifier: Programming Language :: Python :: 3.8
Classifier: Programming Language :: Python :: 3.9
Classifier: Programming Language :: Python :: 3.10
Classifier: Programming Language :: Python :: 3.11
Requires-Python: >=3.7
License-File: LICENSE
